fabricatio_judge/__init__.py
fabricatio_judge/py.typed
fabricatio_judge/capabilities/__init__.py
fabricatio_judge/capabilities/advanced_judge.py
fabricatio_judge/models/__init__.py
fabricatio_judge/models/judgement.py
tests/test_judge.py
fabricatio_judge-0.1.11.dist-info/METADATA
fabricatio_judge-0.1.11.dist-info/WHEEL
fabricatio_judge-0.1.11.dist-info/licenses/LICENSE
fabricatio_judge-0.1.11.dist-info/RECORD
