Metadata-Version: 2.4
Name: fabricatio-judge
Version: 0.1.11
Summary: fabricatio-judge extends the Fabricatio ecosystem to provide advanced judgment capabilities for LLM-driven applications.
Project-URL: Homepage, https://github.com/Whth/fabricatio
Project-URL: Repository, https://github.com/Whth/fabricatio
Project-URL: Issues, https://github.com/Whth/fabricatio/issues
Author-email: Whth <zettainspector@foxmail.com>
License: MIT License
License-File: LICENSE
Requires-Python: <=3.14,>=3.12
Requires-Dist: fabricatio-capabilities
Requires-Dist: fabricatio-core
